{
  "memes": [
    {
      "ID": 181913649,
      "name": "Drake Hotline Bling",
      "Alternate Names": ["drakeposting", "drakepost", "drake hotline approves", "drake no yes", "drake like dislike", "drake faces"]
    },
    {
      "ID": 112126428,
      "name": "Distracted Boyfriend",
      "Alternate Names": ["distracted bf", "guy checking out another girl", "man looking at other woman", "jealous girlfriend", "guy looking back", "cheater temptation", "wandering eyes", "disloyal boyfriend"]
    },
    {
      "ID": 87743020,
      "name": "Two Buttons",
      "Alternate Names": ["2 red buttons", "choice button", "which button", "daily struggle", "hard choice to make"]
    },
    {
      "ID": 124822590,
      "name": "Left Exit 12 Off Ramp",
      "Alternate Names": ["car drifts off highway", "sharp turn on road"]
    },
    {
      "ID": 129242436,
      "name": "Change My Mind",
      "Alternate Names": ["Steven Crowder's sign", "prove me wrong"]
    },
    {
      "ID": 438680,
      "name": "Batman Slapping Robin",
      "Alternate Names": []
    },
    {
      "ID": 217743513,
      "name": "UNO Draw 25 Cards",
      "Alternate Names": ["do something you don’t like or draw 25 cards", "uno dilemma", "uno or draw 25", "draw 25"]
    },
    {
      "ID": 131087935,
      "name": "Running Away Balloon",
      "Alternate Names": ["big yellow ball and pink guy", "me vs my hopes and dreams"]
    },
    {
      "ID": 61579,
      "name": "One Does Not Simply",
      "Alternate Names": ["one does not simply walk into morder", "lord of the rings boromir"]
    },
    {
      "ID": 93895088,
      "name": "Expanding Brain",
      "Alternate Names": []
    },
    {
      "ID": 4087833,
      "name": "Waiting Skeleton",
      "Alternate Names": ["skeleton waiting on bench in the park"]
    },
    {
      "ID": 102156234,
      "name": "Mocking Spongebob",
      "Alternate Names": ["spongebob mock", "spongebob chicken", "retarded spongebob", "sarcastic spongebob", "spongebob stupid", "spongebob derp", "spongebob bird", "spongebob mocking face"]
    },
    {
      "ID": 1035805,
      "name": "Boardroom Meeting Suggestion",
      "Alternate Names": ["throw a guy out the boardroom window"]
    },
    {
      "ID": 101470,
      "name": "Ancient Aliens",
      "Alternate Names": ["Giorgio Tsoukalos", "History Channel Guy"]
    },
    {
      "ID": 91538330,
      "name": "X, X Everywhere",
      "Alternate Names": ["woody and buzz lightyear pointing", "toy story", "dicks everywhere", "toystory everywhere"]
    },
    {
      "ID": 188390779,
      "name": "Woman Yelling At Cat",
      "Alternate Names": ["Women yelling", "confused cat", "girl screaming at cat", "angry woman yelling at cat at dinner table", "lady screams at cat", "woman pointing at cat", "smudge the cat"]
    },
    {
      "ID": 97984,
      "name": "Disaster Girl",
      "Alternate Names": []
    },
    {
      "ID": 247375501,
      "name": "Buff Doge vs. Cheems",
      "Alternate Names": ["swole doge vs cheems", "strong doge weak doge", "big doge small doge", "then vs. now", "buff doge vs. crying cheems"]
    },
    {
      "ID": 89370399,
      "name": "Roll Safe Think About It",
      "Alternate Names": ["thinking black guy", "black guy pointing at his head", "can't blank if you don't blank", "smart black dude", "guy tapping head"]
    },
    {
      "ID": 131940431,
      "name": "Gru's Plan",
      "Alternate Names": ["Grus evil plan", "Despicable Me diabolical plan", "Gru's diabolical plan", "gru 4 panel"]
    },
    {
      "ID": 119139145,
      "name": "Blank Nut Button",
      "Alternate Names": ["blank blue button", "smash button", "press button", "button slam"]
    },
    {
      "ID": 61520,
      "name": "Futurama Fry",
      "Alternate Names": ["Not sure if X or Y", "Skeptical Fry"]
    },
    {
      "ID": 222403160,
      "name": "Bernie I Am Once Again Asking For Your Support",
      "Alternate Names": ["bernie sanders commercial", "bernie sanders 2020 campaign", "asking for your financial support", "once again bernie"]
    },
    {
      "ID": 178591752,
      "name": "Tuxedo Winnie The Pooh",
      "Alternate Names": ["winnie the poo", "winnie the pooh drake style", "classy pooh bear", "tuxedo pooh", "winnie pooh", "winnie the pooh tux", "fancy pooh"]
    },
    {
      "ID": 155067746,
      "name": "Surprised Pikachu",
      "Alternate Names": ["shocked pikachu"]
    },
    {
      "ID": 114585149,
      "name": "Inhaling Seagull",
      "Alternate Names": ["inhaling bird"]
    },
    {
      "ID": 5496396,
      "name": "Leonardo Dicaprio Cheers",
      "Alternate Names": ["The Great Gatsby party with Jay Gatsby", "gatsby toast"]
    },
    {
      "ID": 123999232,
      "name": "The Scroll Of Truth",
      "Alternate Names": ["I've finally found it... after 15 years", "nyehhh"]
    },
    {
      "ID": 27813981,
      "name": "Hide the Pain Harold",
      "Alternate Names": ["sad life harold", "maurice"]
    },
    {
      "ID": 61532,
      "name": "The Most Interesting Man In The World",
      "Alternate Names": ["I dont always... but when I do", "Dos Equis Man", "I don't always"]
    },
    {
      "ID": 21735,
      "name": "The Rock Driving",
      "Alternate Names": []
    },
    {
      "ID": 135256802,
      "name": "Epic Handshake",
      "Alternate Names": ["arm wrestling", "holding hands", "grasping hands", "epic hand shake", "black white arms agreement"]
    },
    {
      "ID": 100777631,
      "name": "Is This A Pigeon",
      "Alternate Names": ["is this a pidgeon", "anime butterfly guy", "oblivious butterfly man anime", "is this a bird", "is this butterfly"]
    },
    {
      "ID": 226297822,
      "name": "Panik Kalm Panik",
      "Alternate Names": ["panic calm panic", "meme man wurds"]
    },
    {
      "ID": 80707627,
      "name": "Sad Pablo Escobar",
      "Alternate Names": ["pablo escobar waiting", "man waiting", "waiting man", "lonely man", "narcos waiting", "narcos bored", "narcos alone"]
    },
    {
      "ID": 124055727,
      "name": "Y'all Got Any More Of That",
      "Alternate Names": ["Tyrone Biggums", "Dave Chappelle", "Chappelles Show", "yall got any more of that stuff", "powder lips neck scratch"]
    },
    {
      "ID": 8072285,
      "name": "Doge",
      "Alternate Names": ["Shiba Inu"]
    },
    {
      "ID": 148909805,
      "name": "Monkey Puppet",
      "Alternate Names": ["monkey looking away", "monkey puppet avoids eye contact", "hiding in plain sight", "awkward look monkey"]
    },
    {
      "ID": 28251713,
      "name": "Oprah You Get A",
      "Alternate Names": ["oprah giveway", "oprah winfrey", "oprah you get a car", "everyone gets a car", "you get an oprah", "oprah excited"]
    },
    {
      "ID": 61585,
      "name": "Bad Luck Brian",
      "Alternate Names": []
    },
    {
      "ID": 252600902,
      "name": "Always Has Been",
      "Alternate Names": ["wait it's all just ohio", "two astronauts betrayal", "astronaut gun", "astronaut lie", "astronaut discovers conspiracy theory", "always have been", "it always was"]
    },
    {
      "ID": 101288,
      "name": "Third World Skeptical Kid",
      "Alternate Names": ["African skeptical child"]
    },
    {
      "ID": 61539,
      "name": "First World Problems",
      "Alternate Names": ["fwp", "woman crying"]
    },
    {
      "ID": 161865971,
      "name": "Marked Safe From",
      "Alternate Names": ["facebook marked safe", "marked safe flag", "marked safe today", "facebook safe from"]
    },
    {
      "ID": 134797956,
      "name": "American Chopper Argument",
      "Alternate Names": ["orange county choppers fight", "american chopper hot take"]
    },
    {
      "ID": 6235864,
      "name": "Finding Neverland",
      "Alternate Names": ["Johnny Depp And Little Kid Crying"]
    },
    {
      "ID": 61556,
      "name": "Grandma Finds The Internet",
      "Alternate Names": []
    },
    {
      "ID": 180190441,
      "name": "They're The Same Picture",
      "Alternate Names": ["it's the same picture", "corporate needs you to find the differences between this picture and this picture", "pam from the office", "office same picture", "spot the difference"]
    },
    {
      "ID": 175540452,
      "name": "Unsettled Tom",
      "Alternate Names": ["tom face", "concerned tom", "tom and jerry", "disgusted tom", "surprised tom", "tom staring down"]
    },
    {
      "ID": 61527,
      "name": "Y U No",
      "Alternate Names": []
    },
    {
      "ID": 84341851,
      "name": "Evil Kermit",
      "Alternate Names": ["kermit me to me", "kermit inner me", "sith kermit", "kermit dark side"]
    },
    {
      "ID": 110163934,
      "name": "I Bet He's Thinking About Other Women",
      "Alternate Names": ["i bet he's thinking of other woman", "i bet he's thinking about other girls", "couple in bed", "i wonder what he's thinking", "guy thinking in bed"]
    },
    {
      "ID": 91545132,
      "name": "Trump Bill Signing",
      "Alternate Names": ["executive order trump"]
    },
    {
      "ID": 61544,
      "name": "Success Kid",
      "Alternate Names": ["Motivation Baby", "Motivation Kid", "Success Baby"]
    },
    {
      "ID": 563423,
      "name": "That Would Be Great",
      "Alternate Names": ["Bill Lumbergh", "office space", "yea that'd be great"]
    },
    {
      "ID": 3218037,
      "name": "This Is Where I'd Put My Trophy If I Had One",
      "Alternate Names": []
    },
    {
      "ID": 61546,
      "name": "Brace Yourselves X is Coming",
      "Alternate Names": ["imminent ned from game of thrones", "brace yourselves winter is coming", "brace yourself"]
    },
    {
      "ID": 135678846,
      "name": "Who Killed Hannibal",
      "Alternate Names": ["Eric Andre shooting Hannibal Buress", "why would they do this"]
    },
    {
      "ID": 14371066,
      "name": "Star Wars Yoda",
      "Alternate Names": ["master yoda"]
    },
    {
      "ID": 55311130,
      "name": "This Is Fine",
      "Alternate Names": ["this is fine dog", "dog house fire", "dog in burning house", "house on fire"]
    },
    {
      "ID": 61582,
      "name": "Creepy Condescending Wonka",
      "Alternate Names": ["willy wonka stare", "sarcastic wonka", "tell me more about X", "tell me again", "gene wilder"]
    },
    {
      "ID": 405658,
      "name": "Grumpy Cat",
      "Alternate Names": []
    },
    {
      "ID": 196652226,
      "name": "Spongebob Ight Imma Head Out",
      "Alternate Names": ["Ight Imma Head Out", "aight imma head out", "spongebob aight", "alright I'm out", "spongebob getting out of chair"]
    },
    {
      "ID": 61533,
      "name": "X All The Y",
      "Alternate Names": ["all the things"]
    },
    {
      "ID": 101511,
      "name": "Don't You Squidward",
      "Alternate Names": ["spongebob grinning", "spongebob smirk face", "smug spongebob"]
    },
    {
      "ID": 16464531,
      "name": "But That's None Of My Business",
      "Alternate Names": ["Kermit the frog", "kermit drinking lipton iced tea"]
    },
    {
      "ID": 79132341,
      "name": "Bike Fall",
      "Alternate Names": ["falling off bike", "baton roue", "stick in bike wheel", "bike stick", "bicycle stick", "bike blame", "falling bike"]
    },
    {
      "ID": 1509839,
      "name": "Captain Picard Facepalm",
      "Alternate Names": ["star trek face palm"]
    },
    {
      "ID": 195515965,
      "name": "Clown Applying Makeup",
      "Alternate Names": ["putting on clown makeup", "clown face", "clown paint", "becoming a clown"]
    },
    {
      "ID": 101287,
      "name": "Third World Success Kid",
      "Alternate Names": ["happy african child", "african kids dancing"]
    },
    {
      "ID": 235589,
      "name": "Evil Toddler",
      "Alternate Names": ["evil baby"]
    },
    {
      "ID": 100947,
      "name": "Matrix Morpheus",
      "Alternate Names": ["what if I told you"]
    },
    {
      "ID": 61516,
      "name": "Philosoraptor",
      "Alternate Names": ["green dinosaur", "dinosaur wondering"]
    },
    {
      "ID": 99683372,
      "name": "Sleeping Shaq",
      "Alternate Names": ["i sleep", "real shit"]
    },
    {
      "ID": 132769734,
      "name": "Hard To Swallow Pills",
      "Alternate Names": ["hard pills to swallow"]
    },
    {
      "ID": 14230520,
      "name": "Black Girl Wat",
      "Alternate Names": ["confused black girl", "black girl with hand out", "seriously black girl"]
    },
    {
      "ID": 259237855,
      "name": "Laughing Leo",
      "Alternate Names": ["Leonardo DiCaprio laughing", "Django Laughing Leo", "Django Unchained laugh", "laughing while holding a drink", "Calvin Candie laugh"]
    },
    {
      "ID": 245898,
      "name": "Picard Wtf",
      "Alternate Names": ["captain jean-luc picard star trek", "annoyed picard", "why the fuck would you"]
    },
    {
      "ID": 922147,
      "name": "Laughing Men In Suits",
      "Alternate Names": ["Men laughing", "And then I said", "And then I told them", "rich men laughing"]
    },
    {
      "ID": 101440,
      "name": "10 Guy",
      "Alternate Names": ["Really High Guy", "Stoner Stanley", "Brainwashed Bob", "stoned guy", "ten guy"]
    },
    {
      "ID": 101910402,
      "name": "Who Would Win?",
      "Alternate Names": []
    },
    {
      "ID": 61580,
      "name": "Too Damn High",
      "Alternate Names": ["The rent is too damn high"]
    },
    {
      "ID": 101716,
      "name": "Yo Dawg Heard You",
      "Alternate Names": ["Xzibit", "Yo dawg we heard you like Y so we put some X in your X so you can Y while you Y"]
    },
    {
      "ID": 259680,
      "name": "Am I The Only One Around Here",
      "Alternate Names": ["Angry Walter from The Big Lebowski"]
    },
    {
      "ID": 40945639,
      "name": "Dr Evil Laser",
      "Alternate Names": ["Dr. Evil quotation marks", "Dr Evil Air Quotes"]
    },
    {
      "ID": 109765,
      "name": "I'll Just Wait Here",
      "Alternate Names": ["waiting skeleton"]
    },
    {
      "ID": 9440985,
      "name": "Face You Make Robert Downey Jr",
      "Alternate Names": []
    },
    {
      "ID": 61581,
      "name": "Put It Somewhere Else Patrick",
      "Alternate Names": ["patrick from spongebob"]
    },
    {
      "ID": 56225174,
      "name": "Be Like Bill",
      "Alternate Names": ["bill the stick figure with a hat"]
    },
    {
      "ID": 163573,
      "name": "Imagination Spongebob",
      "Alternate Names": ["spongebob rainbow", "nobody cares"]
    },
    {
      "ID": 12403754,
      "name": "Bad Pun Dog",
      "Alternate Names": ["joke dog", "whisper joke dog", "happy husky", "joke telling husky", "pun husky"]
    },
    {
      "ID": 29617627,
      "name": "Look At Me",
      "Alternate Names": ["I'm the captain now", "captain phillips"]
    },
    {
      "ID": 460541,
      "name": "Jack Sparrow Being Chased",
      "Alternate Names": ["pirates of the caribbean"]
    },
    {
      "ID": 21604248,
      "name": "Mugatu So Hot Right Now",
      "Alternate Names": ["Mugatu from Zoolander", "Will Farrell"]
    },
    {
      "ID": 195389,
      "name": "Sparta Leonidas",
      "Alternate Names": ["Leonidas from the movie 300"]
    },
    {
      "ID": 1367068,
      "name": "I Should Buy A Boat Cat",
      "Alternate Names": ["sophisticated cat", "fancy cat", "newspaper cat"]
    },
    {
      "ID": 444501,
      "name": "Maury Lie Detector",
      "Alternate Names": ["The lie detector determined that was a lie. The fact that you X determined that was a lie.", "Maury Povich."]
    },
    {
      "ID": 766986,
      "name": "Aaaaand Its Gone",
      "Alternate Names": ["and it's gone", "south park banker guy"]
    },
    {
      "ID": 100955,
      "name": "Confession Bear",
      "Alternate Names": []
    },
    {
      "ID": 6531067,
      "name": "See Nobody Cares",
      "Alternate Names": ["Jurassic Park Dennis"]
    }
  ]
}
